imagescraper_mavi/__init__.py
imagescraper_mavi/scraper.py
imagescraper_mavi-0.1.3.dist-info/METADATA
imagescraper_mavi-0.1.3.dist-info/WHEEL
imagescraper_mavi-0.1.3.dist-info/entry_points.txt
imagescraper_mavi-0.1.3.dist-info/top_level.txt
imagescraper_mavi-0.1.3.dist-info/RECORD
